LICENSE
MANIFEST.in
README.md
pyproject.toml
setup.py
cgat/AGP.py
cgat/AString.py
cgat/Bed.py
cgat/Blat.py
cgat/FastaIterator.py
cgat/Fastq.py
cgat/GFF3.py
cgat/GTF.py
cgat/GeneModelAnalysis.pyx
cgat/Genomics.py
cgat/Glam2.py
cgat/Glam2Scan.py
cgat/Histogram.py
cgat/Histogram2D.py
cgat/IndexedFasta.py
cgat/IndexedGenome.py
cgat/Intervals.py
cgat/Iterators.py
cgat/MEME.py
cgat/Masker.py
cgat/MatrixTools.py
cgat/Motifs.py
cgat/RLE.py
cgat/RateEstimation.py
cgat/SequenceProperties.py
cgat/SetTools.py
cgat/Sra.py
cgat/Stats.py
cgat/Tree.py
cgat/TreeTools.py
cgat/VCF.py
cgat/Variants.py
cgat/__init__.py
cgat/cgat.py
cgat/dictzip.py
cgat/makeGeneset.py
cgat.egg-info/PKG-INFO
cgat.egg-info/SOURCES.txt
cgat.egg-info/dependency_links.txt
cgat.egg-info/entry_points.txt
cgat.egg-info/not-zip-safe
cgat.egg-info/requires.txt
cgat.egg-info/top_level.txt
cgat/BamTools/bamtools.pyx
cgat/BamTools/geneprofile.pyx
cgat/BamTools/peakshape.pyx
cgat/Components/Components.pyx
cgat/Components/connected_components.cpp
cgat/Components/connected_components.h
cgat/FastqTools/fastqtools.pyx
cgat/NCL/__init__.py
cgat/NCL/cnestedlist.pyx
cgat/NCL/default.h
cgat/NCL/intervaldb.c
cgat/NCL/intervaldb.h
cgat/VCFTools/vcftools.pyx
cgat/tools/__init__.py
cgat/tools/bam2bam.py
cgat/tools/bam2bam_split_reads.py
cgat/tools/bam2bed.py
cgat/tools/bam2depth.py
cgat/tools/bam2fasta.py
cgat/tools/bam2fastq.py
cgat/tools/bam2geneprofile.py
cgat/tools/bam2stats.py
cgat/tools/bam2wiggle.py
cgat/tools/bam2window_stats.py
cgat/tools/bam_compare_alignments.py
cgat/tools/bam_pileup2tsv.py
cgat/tools/bam_vs_bam.py
cgat/tools/bam_vs_bed.py
cgat/tools/bam_vs_gtf.py
cgat/tools/bams2bam.py
cgat/tools/bcl2fastq.py
cgat/tools/bed2bed.py
cgat/tools/bed2fasta.py
cgat/tools/bed2gff.py
cgat/tools/bed2graph.py
cgat/tools/bed2stats.py
cgat/tools/bed2table.py
cgat/tools/bed_vs_bed.py
cgat/tools/beds2beds.py
cgat/tools/beds2counts.py
cgat/tools/cgat_get_options.py
cgat/tools/cgat_rebuild_extensions.py
cgat/tools/cgat_script_template.py
cgat/tools/csv2csv.py
cgat/tools/csvs2csv.py
cgat/tools/data2histogram.py
cgat/tools/diff_bam.py
cgat/tools/diff_bed.py
cgat/tools/diff_chains.py
cgat/tools/diff_fasta.py
