Metadata-Version: 2.1
Name: cgat
Version: 0.7.10
Summary: cgat : the Computational Genomics Analysis Toolkit
Author-email: Adam Cribbs <adam.cribbs@ndorms.ox.ac.uk>
License: MIT
Project-URL: Source, https://github.com/cgat-developers/cgat-apps/
Project-URL: Bug_Tracker, https://github.com/cgat-developers/cgat-apps/issues/
Project-URL: Documentation, https://cgat-developers.github.io/cgat-core/
Keywords: computational genomics
Classifier: Development Status :: 3 - Alpha
Classifier: Intended Audience :: Science/Research
Classifier: Intended Audience :: Developers
Classifier: License :: OSI Approved
Classifier: Programming Language :: Python
Classifier: Topic :: Software Development
Classifier: Topic :: Scientific/Engineering
Classifier: Operating System :: POSIX
Classifier: Operating System :: Unix
Classifier: Operating System :: MacOS
Requires-Python: >=3.10
License-File: LICENSE
Requires-Dist: Cython>=0.29.35
Requires-Dist: numpy
Requires-Dist: pysam
